zotero_mcp/__init__.py
zotero_mcp/__main__.py
zotero_mcp/main.py
zotero_mcp/domain/__init__.py
zotero_mcp/domain/entities/__init__.py
zotero_mcp/domain/entities/batch_result.py
zotero_mcp/domain/entities/collection.py
zotero_mcp/domain/entities/reference.py
zotero_mcp/infrastructure/__init__.py
zotero_mcp/infrastructure/mappers/__init__.py
zotero_mcp/infrastructure/mappers/pubmed_mapper.py
zotero_mcp/infrastructure/mcp/__init__.py
zotero_mcp/infrastructure/mcp/analytics_tools.py
zotero_mcp/infrastructure/mcp/basic_read_tools.py
zotero_mcp/infrastructure/mcp/batch_tools.py
zotero_mcp/infrastructure/mcp/collection_tools.py
zotero_mcp/infrastructure/mcp/collection_utils.py
zotero_mcp/infrastructure/mcp/config.py
zotero_mcp/infrastructure/mcp/interactive_tools.py
zotero_mcp/infrastructure/mcp/metadata_fetcher.py
zotero_mcp/infrastructure/mcp/pubmed_tools.py
zotero_mcp/infrastructure/mcp/resources.py
zotero_mcp/infrastructure/mcp/saved_search_tools.py
zotero_mcp/infrastructure/mcp/search_helpers.py
zotero_mcp/infrastructure/mcp/search_tools.py
zotero_mcp/infrastructure/mcp/server.py
zotero_mcp/infrastructure/mcp/smart_tools.py
zotero_mcp/infrastructure/mcp/validation.py
zotero_mcp/infrastructure/pubmed/__init__.py
zotero_mcp/infrastructure/zotero_client/__init__.py
zotero_mcp/infrastructure/zotero_client/client.py
zotero_mcp/infrastructure/zotero_client/client_base.py
zotero_mcp/infrastructure/zotero_client/client_read.py
zotero_mcp/infrastructure/zotero_client/client_write.py
zotero_keeper-1.10.1.dist-info/METADATA
zotero_keeper-1.10.1.dist-info/WHEEL
zotero_keeper-1.10.1.dist-info/entry_points.txt
zotero_keeper-1.10.1.dist-info/RECORD
