Metadata-Version: 2.4
Name: zotero-keeper
Version: 1.10.1
Summary: MCP Server for managing local Zotero libraries - enables AI assistants to read and write bibliographic references
Project-URL: Homepage, https://github.com/u9401066/zotero-keeper
Project-URL: Documentation, https://github.com/u9401066/zotero-keeper#readme
Project-URL: Repository, https://github.com/u9401066/zotero-keeper.git
Project-URL: Issues, https://github.com/u9401066/zotero-keeper/issues
Project-URL: Changelog, https://github.com/u9401066/zotero-keeper/blob/main/CHANGELOG.md
Author: Zotero Keeper Contributors
License: Apache-2.0
Keywords: ai,bibliography,mcp,model-context-protocol,reference-manager,zotero
Classifier: Development Status :: 4 - Beta
Classifier: Intended Audience :: Developers
Classifier: Intended Audience :: Science/Research
Classifier: License :: OSI Approved :: Apache Software License
Classifier: Operating System :: OS Independent
Classifier: Programming Language :: Python :: 3
Classifier: Programming Language :: Python :: 3.11
Classifier: Programming Language :: Python :: 3.12
Classifier: Topic :: Scientific/Engineering
Classifier: Topic :: Software Development :: Libraries :: Python Modules
Requires-Python: >=3.11
Requires-Dist: httpx>=0.27.0
Requires-Dist: mcp>=1.0.0
Requires-Dist: pydantic-settings>=2.0.0
Requires-Dist: pydantic>=2.0.0
Requires-Dist: rapidfuzz>=3.0.0
Provides-Extra: all
Requires-Dist: pubmed-search-mcp>=0.1.8; extra == 'all'
Requires-Dist: rapidfuzz>=3.0.0; extra == 'all'
Provides-Extra: dev
Requires-Dist: mypy>=1.0.0; extra == 'dev'
Requires-Dist: pytest-asyncio>=0.21.0; extra == 'dev'
Requires-Dist: pytest-cov>=4.0.0; extra == 'dev'
Requires-Dist: pytest>=7.0.0; extra == 'dev'
Requires-Dist: ruff>=0.1.0; extra == 'dev'
Provides-Extra: pubmed
Requires-Dist: pubmed-search-mcp>=0.1.8; extra == 'pubmed'
